techiaith/py.typed
techiaith/version.py
techiaith/tts/testun/date_norm.py
techiaith/tts/testun/known_phrases.py
techiaith/tts/testun/lexicon.py
techiaith/tts/testun/lookups.py
techiaith/tts/testun/number_norm.py
techiaith/tts/testun/time_norm.py
techiaith/tts/testun/data/__init__.py
techiaith/tts/testun/data/lecsicon_cc0.txt
techiaith_tts-0.1.6.dist-info/LICENSE
techiaith_tts-0.1.6.dist-info/METADATA
techiaith_tts-0.1.6.dist-info/WHEEL
techiaith_tts-0.1.6.dist-info/top_level.txt
techiaith_tts-0.1.6.dist-info/RECORD
