Metadata-Version: 2.1
Name: techiaith-tts
Version: 0.1.6
Home-page: https://github.com/techiaith/techiaith-tts
Author: Allen Institute for Artificial Intelligence
Author-email: contact@allenai.org
License: Apache
Classifier: Intended Audience :: Science/Research
Classifier: Development Status :: 3 - Alpha
Classifier: License :: OSI Approved :: Apache Software License
Classifier: Programming Language :: Python :: 3
Classifier: Topic :: Scientific/Engineering :: Artificial Intelligence
Requires-Python: >=3.8
License-File: LICENSE
Provides-Extra: dev
Requires-Dist: flake8 ; extra == 'dev'
Requires-Dist: mypy (<1.5,>=1.0) ; extra == 'dev'
Requires-Dist: black (<24.0,>=23.0) ; extra == 'dev'
Requires-Dist: isort (<5.13,>=5.12) ; extra == 'dev'
Requires-Dist: pytest ; extra == 'dev'
Requires-Dist: pytest-sphinx ; extra == 'dev'
Requires-Dist: pytest-cov ; extra == 'dev'
Requires-Dist: twine (>=1.11.0) ; extra == 'dev'
Requires-Dist: setuptools ; extra == 'dev'
Requires-Dist: wheel ; extra == 'dev'
Requires-Dist: Sphinx (<7.1.0,>=4.3.0) ; extra == 'dev'
Requires-Dist: furo (==2023.5.20) ; extra == 'dev'
Requires-Dist: myst-parser (<2.1.0,>=0.15.2) ; extra == 'dev'
Requires-Dist: sphinx-copybutton (==0.5.2) ; extra == 'dev'
Requires-Dist: sphinx-autobuild (==2021.3.14) ; extra == 'dev'
Requires-Dist: sphinx-autodoc-typehints ; extra == 'dev'
Requires-Dist: packaging ; extra == 'dev'
